{
  "format_version": "1.13.0",
  "minecraft:feature_rules": {
    "description": {
      "identifier": "isl:o_v_isl_fr_birch_forest",
      "places_feature": "isl:islands/isl_birch_forest_c_assy"
    },
    "conditions": {
      "placement_pass": "final_pass",
      "minecraft:biome_filter": [
        {
          "any_of": [
            {
              "test": "has_biome_tag",
              "operator": "==",
              "value": "birch"
            }
          ]
        }
      ]
    },
    "distribution": {
      "scatter_chance": "(math.mod((variable.originx/16)*(variable.originz/16),26)==1)?100:0",
      "iterations": 1,
      "x": 0,
      "z": 0,
      "y": 63
    }
  }
}